dlinfo/__init__.py
dlinfo/_glibc.py
dlinfo/_macosx.py
dlinfo-1.2.1.dist-info/LICENSE
dlinfo-1.2.1.dist-info/METADATA
dlinfo-1.2.1.dist-info/WHEEL
dlinfo-1.2.1.dist-info/top_level.txt
dlinfo-1.2.1.dist-info/RECORD
